setup.py
txretry/__init__.py
txretry/retry.py
txretry.egg-info/PKG-INFO
txretry.egg-info/SOURCES.txt
txretry.egg-info/dependency_links.txt
txretry.egg-info/pbr.json
txretry.egg-info/requires.txt
txretry.egg-info/top_level.txt
txretry/test/__init__.py
txretry/test/test_retry.py