Metadata-Version: 1.1
Name: txretry
Version: 1.0.0
Summary: A Twisted class for retrying failing calls with a customizable back-off schedule.
Home-page: https://github.com/fluidinfo/txretry
Author: Fluidinfo Inc.
Author-email: terry@jon.es
License: UNKNOWN
Download-URL: https://github.com/fluidinfo/txretry
Keywords: twisted function retry
Platform: UNKNOWN
Classifier: Programming Language :: Python
Classifier: Framework :: Twisted
Classifier: Development Status :: 4 - Beta
Classifier: Intended Audience :: Developers
Classifier: License :: OSI Approved :: Apache Software License
Classifier: Operating System :: OS Independent
Classifier: Topic :: Software Development :: Libraries :: Python Modules
Provides: txretry
